mend_azure_wi_sync/__init__.py
mend_azure_wi_sync/_version.py
mend_azure_wi_sync/azure_wi_sync.py
mend_azure_wi_sync/config.py
mend_azure_wi_sync/conftest.py
mend_azure_wi_sync/core.py
mend_azure_wi_sync-25.5.1.dist-info/LICENSE
mend_azure_wi_sync-25.5.1.dist-info/METADATA
mend_azure_wi_sync-25.5.1.dist-info/WHEEL
mend_azure_wi_sync-25.5.1.dist-info/entry_points.txt
mend_azure_wi_sync-25.5.1.dist-info/top_level.txt
mend_azure_wi_sync-25.5.1.dist-info/RECORD
