Metadata-Version: 2.1
Name: mend_azure_wi_sync
Version: 25.5.1
Summary: Synchronize Mend SCA security alerts with Azure Work Items
Home-page: https://github.com/mend-toolkit/azure-wi-sync
Author: Mend Professional Services
Author-email: ps@mend.io
License: LICENSE.txt
Classifier: Programming Language :: Python :: 3.9
Classifier: Programming Language :: Python :: 3.10
Classifier: Programming Language :: Python :: 3.11
Classifier: License :: OSI Approved :: Apache Software License
Classifier: Operating System :: OS Independent
Requires-Python: >=3.9
License-File: LICENSE
Requires-Dist: certifi~=2023.11.17
Requires-Dist: charset-normalizer~=3.0.1
Requires-Dist: DateTime~=5.1
Requires-Dist: idna~=3.4
Requires-Dist: isodate~=0.6.1
Requires-Dist: msrest~=0.6.0
Requires-Dist: oauthlib~=3.2.2
Requires-Dist: pytz~=2023.3
Requires-Dist: requests~=2.31.0
Requires-Dist: requests-oauthlib~=1.3.1
Requires-Dist: six~=1.16.0
Requires-Dist: sqlparse~=0.4.4
Requires-Dist: tzdata~=2022.1
Requires-Dist: urllib3~=2.1.0
Requires-Dist: vsts~=0.1.25
Requires-Dist: zope.interface~=6.0
Requires-Dist: setuptools~=69.0.3
Requires-Dist: pytest~=7.3.1
